{
  "Routes": [
    // ----- IDENTITY CONTROLLER ----- //
    
    // Публичные методы (без авторизации)
    {
      "UpstreamPathTemplate": "/identity/login",
      "UpstreamHttpMethod": [ "POST", "OPTIONS" ],
      "DownstreamPathTemplate": "/api/identity/login",
      "DownstreamScheme": "http",
      "DownstreamHostAndPorts": [
        {
          "Host": "localhost",
          "Port": 5249
        }
      ],
      "AuthenticationOptions": {
        "AuthenticationProviderKey": null,
        "AllowedScopes": []
      }
    },
    {
      "UpstreamPathTemplate": "/identity/refresh-token",
      "UpstreamHttpMethod": [ "POST", "OPTIONS" ],
      "DownstreamPathTemplate": "/api/identity/refresh-token",
      "DownstreamScheme": "http",
      "DownstreamHostAndPorts": [
        {
          "Host": "localhost",
          "Port": 5249
        }
      ],
      "AuthenticationOptions": {
        "AuthenticationProviderKey": null,
        "AllowedScopes": []
      }
    },
    {
      "UpstreamPathTemplate": "/identity/revoke-token",
      "UpstreamHttpMethod": [ "POST", "OPTIONS" ],
      "DownstreamPathTemplate": "/api/identity/revoke-token",
      "DownstreamScheme": "http",
      "DownstreamHostAndPorts": [
        {
          "Host": "localhost",
          "Port": 5249
        }
      ],
      "AuthenticationOptions": {
        "AuthenticationProviderKey": null,
        "AllowedScopes": []
      }
    },
    {
      "UpstreamPathTemplate": "/identity/register",
      "UpstreamHttpMethod": [ "POST", "OPTIONS" ],
      "DownstreamPathTemplate": "/api/identity/register",
      "DownstreamScheme": "http",
      "DownstreamHostAndPorts": [
        {
          "Host": "localhost",
          "Port": 5249
        }
      ],
      "AuthenticationOptions": {
        "AuthenticationProviderKey": null,
        "AllowedScopes": []
      }
    },
    {
      "UpstreamPathTemplate": "/identity/validate",
      "UpstreamHttpMethod": [ "GET", "OPTIONS" ],
      "DownstreamPathTemplate": "/api/identity/validate",
      "DownstreamScheme": "http",
      "DownstreamHostAndPorts": [
        {
          "Host": "localhost",
          "Port": 5249
        }
      ],
      "AuthenticationOptions": {
        "AuthenticationProviderKey": null,
        "AllowedScopes": []
      }
    },

    // Защищённые методы (требуют JWT)
    {
      "UpstreamPathTemplate": "/identity/update-password",
      "UpstreamHttpMethod": [ "PUT", "OPTIONS" ],
      "DownstreamPathTemplate": "/api/identity/update-password",
      "DownstreamScheme": "http",
      "DownstreamHostAndPorts": [
        {
          "Host": "localhost",
          "Port": 5249
        }
      ],
      "AuthenticationOptions": {
        "AuthenticationProviderKey": "Bearer",
        "AllowedScopes": []
      }
    },


    // ----- PASSWORD RECOVERY CONTROLLER ----- //
    {
      "UpstreamPathTemplate": "/password-recovery/request",
      "UpstreamHttpMethod": [ "POST", "OPTIONS" ],
      "DownstreamPathTemplate": "/api/password-recovery/request",
      "DownstreamScheme": "http",
      "DownstreamHostAndPorts": [
        {
          "Host": "localhost",
          "Port": 5249
        }
      ],
      "AuthenticationOptions": {
        "AuthenticationProviderKey": null,
        "AllowedScopes": []
      }
    },
    {
      "UpstreamPathTemplate": "/password-recovery/confirm",
      "UpstreamHttpMethod": [ "POST", "OPTIONS" ],
      "DownstreamPathTemplate": "/api/password-recovery/confirm",
      "DownstreamScheme": "http",
      "DownstreamHostAndPorts": [
        {
          "Host": "localhost",
          "Port": 5249
        }
      ],
      "AuthenticationOptions": {
        "AuthenticationProviderKey": null,
        "AllowedScopes": []
      }
    }
  ]
}